setup.py
document_history/__init__.py
document_history.egg-info/PKG-INFO
document_history.egg-info/SOURCES.txt
document_history.egg-info/dependency_links.txt
document_history.egg-info/not-zip-safe
document_history.egg-info/requires.txt
document_history.egg-info/top_level.txt