Metadata-Version: 1.0
Name: document-history
Version: 0.1
Summary: MongoEngine Document Versionning for Humans
Home-page: https://github.com/Martikos/document_history
Author: Marc Adam
Author-email: marc.m.adam@gmail.com
License: MIT
Platform: UNKNOWN
Classifier: Intended Audience :: Developers
Classifier: License :: OSI Approved :: MIT License
Classifier: Programming Language :: Python :: 2.7
Classifier: Programming Language :: Python :: 3
